CHANGES.txt
README.txt
bootstrap.py
buildout.cfg
setup.py
src/gocept/__init__.py
src/gocept.async.egg-info/PKG-INFO
src/gocept.async.egg-info/SOURCES.txt
src/gocept.async.egg-info/dependency_links.txt
src/gocept.async.egg-info/namespace_packages.txt
src/gocept.async.egg-info/not-zip-safe
src/gocept.async.egg-info/requires.txt
src/gocept.async.egg-info/top_level.txt
src/gocept/async/README.txt
src/gocept/async/__init__.py
src/gocept/async/configure.zcml
src/gocept/async/ftesting.zcml
src/gocept/async/task.py
src/gocept/async/tests.py