Metadata-Version: 1.0
Name: gocept.async
Version: 0.3.3
Summary: Asynchronous function calls using lovely.remotetask
Home-page: http://pypi.python.org/pypi/gocept.async
Author: gocept gmbh & co. kg
Author-email: developers@gocept.com
License: ZPL 2.1
Keywords: zope3 async asynchronous function
Platform: UNKNOWN
Classifier: Development Status :: 2 - Pre-Alpha
Classifier: Framework :: Zope3
Classifier: Intended Audience :: Developers
Classifier: License :: OSI Approved :: Zope Public License
Classifier: License :: OSI Approved
Classifier: Natural Language :: English
Classifier: Operating System :: OS Independent
Classifier: Programming Language :: Python
Classifier: Topic :: Software Development
